hyperfetch/__init__.py
hyperfetch/alg_samplers.py
hyperfetch/auth_connection.py
hyperfetch/callbacks.py
hyperfetch/manager.py
hyperfetch/tuning.py
hyperfetch/util.py
hyperfetch-1.1.1.dist-info/LICENSE
hyperfetch-1.1.1.dist-info/METADATA
hyperfetch-1.1.1.dist-info/WHEEL
hyperfetch-1.1.1.dist-info/entry_points.txt
hyperfetch-1.1.1.dist-info/top_level.txt
hyperfetch-1.1.1.dist-info/RECORD
