Metadata-Version: 2.1
Name: hyperfetch
Version: 1.1.1
Summary: A tool to optimize and post hyperparameters for your reinforcement learning application. Currently available on Linux and macOS.
Author-email: Karoline Sund Wahl <karolines.wahl@gmail.com>
License: Copyright 2023 Karoline Sund Wahl
Project-URL: Website, https://www.hyperfetch.online/
Project-URL: Source, https://github.com/karolisw/hyperFetch
Keywords: reinforcement learning,hyperparameters,replication
Classifier: Development Status :: 3 - Alpha
Classifier: Intended Audience :: Developers
Classifier: License :: OSI Approved :: BSD License
Classifier: Operating System :: POSIX :: Linux
Classifier: Operating System :: MacOS
Classifier: Programming Language :: Python :: 3.9
Classifier: Programming Language :: Python :: 3.10
Classifier: Framework :: FastAPI
Requires-Python: <3.11.0,>=3.9
License-File: LICENSE
Requires-Dist: setuptools (==64.0.3)
Requires-Dist: swig (==4.0.2)
Requires-Dist: box2d-py (==2.3.8)
Requires-Dist: python-benedict (==0.30.0)
Requires-Dist: codecarbon (==2.1.4)
Requires-Dist: pandas (==2.0.1)
Requires-Dist: PyYAML (==6.0)
Requires-Dist: motor (==3.1.2)
Requires-Dist: numpy (==1.24.3)
Requires-Dist: gym (==0.21.0)
Requires-Dist: torch (>=1.13.1)
Requires-Dist: optuna (==3.1.1)
Requires-Dist: stable-baselines3 (==1.8.0)
Requires-Dist: rl-zoo3 (==1.8.0)
Requires-Dist: python-dotenv (==1.0.0)
Requires-Dist: starlette (==0.26.1)
